pltparams/__init__.py
pltparams/pltparams.py
pltparams-1.0.0.dist-info/licenses/LICENSE
pltparams-1.0.0.dist-info/METADATA
pltparams-1.0.0.dist-info/WHEEL
pltparams-1.0.0.dist-info/top_level.txt
pltparams-1.0.0.dist-info/RECORD
