Metadata-Version: 2.4
Name: pltparams
Version: 1.0.0
Summary: Sets matplotlib parameters for scientific publishing.
Author-email: Gaute Holen <gaute.ah@gmail.com>
License: MIT License
Project-URL: Homepage, https://github.com/GauteHolen/pltparams
Project-URL: Issues, https://github.com/GauteHolen/pltparams/issues
Requires-Python: >=3.8
License-File: LICENSE
Requires-Dist: numpy
Requires-Dist: matplotlib
Dynamic: license-file
